setup.py
fabric_template/__init__.py
fabric_template/nginx.py
fabric_template/supervisor.py
fabric_template.egg-info/PKG-INFO
fabric_template.egg-info/SOURCES.txt
fabric_template.egg-info/dependency_links.txt
fabric_template.egg-info/requires.txt
fabric_template.egg-info/top_level.txt
fabric_template/templates/__init__.py
fabric_template/templates/simple.py