Metadata-Version: 1.0
Name: fabric-template
Version: 0.1.dev5
Summary: A reusable django deploy fabfile
Home-page: https://github.com/waylybaye/fabric-template
Author: waylybaye
Author-email: waylybaye@wayly.net
License: MIT
Platform: UNKNOWN
